duckdown/__init__.py
duckdown/app.py
duckdown/config.py
duckdown/assets/logo.svg
duckdown/assets/vue/feather-sprite.4c3a5e7a.svg
duckdown/assets/vue/index.e44ded4f.js
duckdown/assets/vue/logo.f97ed900.svg
duckdown/assets/vue/manifest.json
duckdown/assets/vue/style.a84e9902.css
duckdown/handlers/__init__.py
duckdown/handlers/access_control.py
duckdown/handlers/base_handler.py
duckdown/handlers/dir_handler.py
duckdown/handlers/editor_handler.py
duckdown/handlers/mark_handler.py
duckdown/handlers/s3_browser.py
duckdown/handlers/site_handler.py
duckdown/handlers/static_files.py
duckdown/templates/login.html
duckdown/templates/vue.html
duckdown/tool/__init__.py
duckdown/tool/create.py
duckdown/tool/publish.py
duckdown/tool/run.py
duckdown/tool/secure.py
duckdown/tool/data/config.ini
duckdown/tool/data/favicon.ico
duckdown/tool/data/index.md
duckdown/tool/data/logo.svg
duckdown/tool/data/robots.txt
duckdown/tool/data/site.css
duckdown/tool/data/site_tmpl.html
duckdown/tool/data/users.json
duckdown/tool/provision/__init__.py
duckdown/tool/provision/credentials.py
duckdown/tool/provision/iam_tools.py
duckdown/tool/provision/route53_tools.py
duckdown/tool/provision/s3_tools.py
duckdown/tool/provision/store.py
duckdown/tool/provision/tasks.py
duckdown/tool/provision/utils.py
duckdown/tool/provision/resources/bucket_policy_tmpl.json
duckdown/tool/provision/resources/cors_tmpl.json
duckdown/tool/provision/resources/error_tmpl.html
duckdown/tool/provision/resources/index_tmpl.html
duckdown/tool/provision/resources/user_policy_tmpl.json
duckdown/utils/__init__.py
duckdown/utils/assets_mixin.py
duckdown/utils/converter_mixin.py
duckdown/utils/encrypt.py
duckdown/utils/folder.py
duckdown/utils/head.py
duckdown/utils/json_utils.py
duckdown/utils/nav.py
duckdown/utils/run_tornado.py
duckdown/utils/s3_folders.py
duckdown/utils/tmpl_loader.py
duckdown-0.0.49.dist-info/LICENSE
duckdown-0.0.49.dist-info/METADATA
duckdown-0.0.49.dist-info/WHEEL
duckdown-0.0.49.dist-info/entry_points.txt
duckdown-0.0.49.dist-info/top_level.txt
duckdown-0.0.49.dist-info/RECORD
