Metadata-Version: 2.1
Name: duckdown
Version: 0.0.49
Summary: UNKNOWN
Home-page: https://github.com/blueshed/duckdown/
License: UNKNOWN
Platform: UNKNOWN
Classifier: Programming Language :: Python :: 3
Classifier: License :: OSI Approved :: MIT License
Classifier: Operating System :: OS Independent
Requires-Dist: invoke
Requires-Dist: tornado
Requires-Dist: markdown
Requires-Dist: pymdown-extensions
Requires-Dist: python-dotenv
Requires-Dist: boto3
Requires-Dist: cryptography
Requires-Dist: tld
